__init__.py
dblp_parser.py
dblp_sax_parser-0.1.dist-info/LICENSE
dblp_sax_parser-0.1.dist-info/METADATA
dblp_sax_parser-0.1.dist-info/WHEEL
dblp_sax_parser-0.1.dist-info/top_level.txt
dblp_sax_parser-0.1.dist-info/RECORD
