Metadata-Version: 2.1
Name: dblp-sax-parser
Version: 0.1
Summary: A parsing package for dblp using the Simple API for XML (SAX)
Author-email: Leon <leonsunwl@gmail.com>
Project-URL: Homepage, https://github.com/leonswl/dblp-sax-parser
Project-URL: Bug Tracker, https://github.com/leonswl/dblp-sax-parser/issues
Classifier: Programming Language :: Python :: 3
Classifier: License :: OSI Approved :: MIT License
Classifier: Operating System :: OS Independent
Requires-Python: >=3.11.3
License-File: LICENSE
Requires-Dist: requests
Requires-Dist: pandas (>=2.0.2)
Requires-Dist: hurry.filesize (>=0.09)
